warden/__init__.py
warden/_version.py
warden/legacy_cli.py
warden/main.py
warden/analysis/__init__.py
warden/analysis/application/__init__.py
warden/analysis/application/analysis_phase.py
warden/analysis/application/convention_detector.py
warden/analysis/application/dependency_graph.py
warden/analysis/application/file_context_analyzer.py
warden/analysis/application/framework_detector.py
warden/analysis/application/integrity_scanner.py
warden/analysis/application/issue_tracker.py
warden/analysis/application/llm_analysis_phase.py
warden/analysis/application/llm_context_analyzer.py
warden/analysis/application/llm_phase_base.py
warden/analysis/application/metrics_aggregator.py
warden/analysis/application/pre_analysis_phase.py
warden/analysis/application/project_purpose_detector.py
warden/analysis/application/project_structure_analyzer.py
warden/analysis/application/result_analyzer.py
warden/analysis/application/service_abstraction_detector.py
warden/analysis/application/statistics_collector.py
warden/analysis/application/discovery/__init__.py
warden/analysis/application/discovery/classifier.py
warden/analysis/application/discovery/discoverer.py
warden/analysis/application/discovery/framework_detector.py
warden/analysis/application/discovery/gitignore_filter.py
warden/analysis/application/discovery/models.py
warden/analysis/application/resolvers/semantic_resolver.py
warden/analysis/domain/__init__.py
warden/analysis/domain/context_weights.py
warden/analysis/domain/enums.py
warden/analysis/domain/file_context.py
warden/analysis/domain/models.py
warden/analysis/domain/project_context.py
warden/analysis/domain/quality_metrics.py
warden/ast/__init__.py
warden/ast/application/__init__.py
warden/ast/application/provider_interface.py
warden/ast/application/provider_loader.py
warden/ast/application/provider_registry.py
warden/ast/domain/__init__.py
warden/ast/domain/enums.py
warden/ast/domain/models.py
warden/ast/providers/__init__.py
warden/ast/providers/python_ast_provider.py
warden_core-1.8.4.dist-info/licenses/LICENSE
warden_core-1.8.4.dist-info/METADATA
warden_core-1.8.4.dist-info/WHEEL
warden_core-1.8.4.dist-info/entry_points.txt
warden_core-1.8.4.dist-info/top_level.txt
warden_core-1.8.4.dist-info/RECORD
