Metadata-Version: 2.4
Name: warden-core
Version: 1.8.4
Summary: Warden - AI Code Guardian for comprehensive code validation
Home-page: https://github.com/alperduzgun/warden-core
Author: Warden Team
Author-email: warden@example.com
Classifier: Development Status :: 3 - Alpha
Classifier: Intended Audience :: Developers
Classifier: Topic :: Software Development :: Quality Assurance
Classifier: Topic :: Software Development :: Testing
Classifier: License :: Other/Proprietary License
Classifier: Programming Language :: Python :: 3
Classifier: Programming Language :: Python :: 3.9
Classifier: Programming Language :: Python :: 3.10
Classifier: Programming Language :: Python :: 3.11
Classifier: Programming Language :: Python :: 3.12
Requires-Python: >=3.9
License-File: LICENSE
Requires-Dist: typer>=0.9.0
Requires-Dist: rich>=13.0.0
Requires-Dist: pyyaml>=6.0
Requires-Dist: httpx>=0.24.0
Requires-Dist: textual>=0.60.0
Requires-Dist: textual-dev>=1.0.0
Requires-Dist: tree-sitter>=0.21.0
Requires-Dist: tree-sitter-javascript>=0.21.0
Requires-Dist: tree-sitter-typescript>=0.21.0
Requires-Dist: tree-sitter-go>=0.21.0
Requires-Dist: pydantic>=2.5.0
Requires-Dist: psutil>=5.9.0
Requires-Dist: structlog>=24.1.0
Requires-Dist: grpcio>=1.59.0
Requires-Dist: grpcio-tools>=1.59.0
Requires-Dist: pydantic-settings>=2.0.0
Requires-Dist: aiofiles>=23.0.0
Requires-Dist: openai>=1.0.0
Requires-Dist: chromadb>=0.4.0
Requires-Dist: sentence-transformers>=2.2.0
Provides-Extra: dev
Requires-Dist: pytest>=7.0.0; extra == "dev"
Requires-Dist: pytest-asyncio>=0.21.0; extra == "dev"
Requires-Dist: black>=23.0.0; extra == "dev"
Requires-Dist: isort>=5.12.0; extra == "dev"
Requires-Dist: mypy>=1.0.0; extra == "dev"
Provides-Extra: cloud
Requires-Dist: qdrant-client>=1.7.0; extra == "cloud"
Dynamic: author
Dynamic: author-email
Dynamic: classifier
Dynamic: description
Dynamic: description-content-type
Dynamic: home-page
Dynamic: license-file
Dynamic: provides-extra
Dynamic: requires-dist
Dynamic: requires-python
Dynamic: summary
